myapp/__init__.py
myapp/admin.py
myapp/apps.py
myapp/models.py
myapp/tests.py
myapp/views.py
myapp/migrations/__init__.py
myapp/templates/my_template.html
myproject/__init__.py
myproject/asgi.py
myproject/settings.py
myproject/urls.py
myproject/wsgi.py
django_aboelezz-0.101.dist-info/METADATA
django_aboelezz-0.101.dist-info/WHEEL
django_aboelezz-0.101.dist-info/top_level.txt
django_aboelezz-0.101.dist-info/RECORD
